odoo/addons/delivery_postlogistics_server_env/README.rst
odoo/addons/delivery_postlogistics_server_env/__init__.py
odoo/addons/delivery_postlogistics_server_env/__manifest__.py
odoo/addons/delivery_postlogistics_server_env/i18n/delivery_postlogistics_server_env.pot
odoo/addons/delivery_postlogistics_server_env/models/__init__.py
odoo/addons/delivery_postlogistics_server_env/models/delivery_carrier.py
odoo/addons/delivery_postlogistics_server_env/readme/CONTRIBUTORS.rst
odoo/addons/delivery_postlogistics_server_env/readme/DESCRIPTION.rst
odoo/addons/delivery_postlogistics_server_env/static/description/icon.png
odoo/addons/delivery_postlogistics_server_env/static/description/index.html
odoo13_addon_delivery_postlogistics_server_env-13.0.1.0.1.dev4.dist-info/METADATA
odoo13_addon_delivery_postlogistics_server_env-13.0.1.0.1.dev4.dist-info/WHEEL
odoo13_addon_delivery_postlogistics_server_env-13.0.1.0.1.dev4.dist-info/top_level.txt
odoo13_addon_delivery_postlogistics_server_env-13.0.1.0.1.dev4.dist-info/RECORD
